[
  {
    "account_id": "c1.inotel.near",
    "public_key": "ed25519:AdRBDme834sua8FqtwxuAYm4XhP2PyYV7ZjeV3cEpmJ5",
    "is_slashed": false,
    "stake": "513919139617675982585977097153",
    "shards": [
      0
    ],
    "num_produced_blocks": 200,
    "num_expected_blocks": 200
  },
  {
    "account_id": "infinite.lux.near",
    "public_key": "ed25519:E8MAM9q5ikkoye81wKiD814GFachTogWwLfE4pZxQwKX",
    "is_slashed": false,
    "stake": "731856049242872685303304127437",
    "shards": [
      0
    ],
    "num_produced_blocks": 300,
    "num_expected_blocks": 300
  },
  {
    "account_id": "node1",
    "public_key": "ed25519:6DSjZ8mvsRZDvFqFxo8tCKePG96omXW7eVYVSySmDk8e",
    "is_slashed": false,
    "stake": "5720087887756958201904799621297",
    "shards": [
      0
    ],
    "num_produced_blocks": 2400,
    "num_expected_blocks": 2400
  },
  {
    "account_id": "node2",
    "public_key": "ed25519:GkDv7nSMS3xcqA45cpMvFmfV1o4fRF6zYo1JRR6mNqg5",
    "is_slashed": false,
    "stake": "5719097026438574977600759006647",
    "shards": [
      0
    ],
    "num_produced_blocks": 2350,
    "num_expected_blocks": 2350
  },
  {
    "account_id": "node3",
    "public_key": "ed25519:ydgzeXHJ5Xyt7M1gXLxqLBW1Ejx6scNV5Nx2pxFM8su",
    "is_slashed": false,
    "stake": "5718024168840572536592829001819",
    "shards": [
      0
    ],
    "num_produced_blocks": 2350,
    "num_expected_blocks": 2350
  },
  {
    "account_id": "pool.48.near",
    "public_key": "ed25519:HkchASewGKi7cHiif44mtB1xd3oxyxsNGd8sLgemKybP",
    "is_slashed": false,
    "stake": "731848034990909564886127972775",
    "shards": [
      0
    ],
    "num_produced_blocks": 300,
    "num_expected_blocks": 300
  },
  {
    "account_id": "pool.appload.near",
    "public_key": "ed25519:5jo9rs39n5tmXv5TnPup1ErQjajhYvZ5YWyS8pnapyLw",
    "is_slashed": false,
    "stake": "1097164031294140244453141368082",
    "shards": [
      0
    ],
    "num_produced_blocks": 450,
    "num_expected_blocks": 450
  },
  {
    "account_id": "pool.jazza-betanet.near",
    "public_key": "ed25519:4cKWhGQHfAZkUix3fcsDBVoRSerFwPD3GUMPNqeUJFgY",
    "is_slashed": false,
    "stake": "1820923415483208140095082644694",
    "shards": [
      0
    ],
    "num_produced_blocks": 750,
    "num_expected_blocks": 750
  },
  {
    "account_id": "pool.projecttent.near",
    "public_key": "ed25519:5cjmmYzjcktwUA3Vqh2dX5PWxEWu8RiWjqnyN4ocJ9YL",
    "is_slashed": false,
    "stake": "340293830569425916279557753898",
    "shards": [
      0
    ],
    "num_produced_blocks": 100,
    "num_expected_blocks": 100
  },
  {
    "account_id": "poolv1.majlovesreg.near",
    "public_key": "ed25519:8VFKemtwwy2gWaRBsRGiypDJUKUjdpe2SRRzBuPCnXRd",
    "is_slashed": false,
    "stake": "1914556237889608332635499924141",
    "shards": [
      0
    ],
    "num_produced_blocks": 800,
    "num_expected_blocks": 800
  }
]