[
  {
    "account_id": "31337x.31337.betanet",
    "public_key": "ed25519:J3yfHuxL17utu8C9SS9XWo3q6dEkMU9BG2JtFDmKvimb",
    "is_slashed": false,
    "stake": "52474162218052135206864836576",
    "shards": [
      0
    ],
    "num_produced_blocks": 100,
    "num_expected_blocks": 100
  },
  {
    "account_id": "777staker.7777nda.betanet",
    "public_key": "ed25519:B1Bm4Y26edSzkGZjF1Avjsrbapab9wz6VLD2JtHBUYsM",
    "is_slashed": false,
    "stake": "82638825896926662617846158624",
    "shards": [
      0
    ],
    "num_produced_blocks": 101,
    "num_expected_blocks": 101
  },
  {
    "account_id": "ag_staking",
    "public_key": "ed25519:5RFyRfrUetiG4bxmWKtRqbXtDtT2acngUBZYrCXk2Mja",
    "is_slashed": false,
    "stake": "162701366688922355444928028746",
    "shards": [
      0
    ],
    "num_produced_blocks": 300,
    "num_expected_blocks": 301
  },
  {
    "account_id": "averonix",
    "public_key": "ed25519:4Je5ZNRHW6usvkNi1coviAAbeFCct7qLTjCriWFP8Ua1",
    "is_slashed": false,
    "stake": "119273364117692558006031483239",
    "shards": [
      0
    ],
    "num_produced_blocks": 0,
    "num_expected_blocks": 201
  },
  {
    "account_id": "awesome",
    "public_key": "ed25519:AVb1yZULrZ117PHMynbZnUWdkanesudUYKAAMEeaSVk8",
    "is_slashed": false,
    "stake": "77556589064359433963445132915",
    "shards": [
      0
    ],
    "num_produced_blocks": 96,
    "num_expected_blocks": 100
  },
  {
    "account_id": "bambarello",
    "public_key": "ed25519:EWvyjf18NBvVT2fmEy3ipcfcjmnHvP5qFew49iC5czsv",
    "is_slashed": false,
    "stake": "118071779997458845668604435882",
    "shards": [
      0
    ],
    "num_produced_blocks": 0,
    "num_expected_blocks": 200
  },
  {
    "account_id": "chorus-one-pool-v1.stakehouse.betanet",
    "public_key": "ed25519:2QkPycJAwY73zqZvnnJHBWrCchsxB8YnrYbLRwVKNZAF",
    "is_slashed": false,
    "stake": "103335863514190423853994810624",
    "shards": [
      0
    ],
    "num_produced_blocks": 200,
    "num_expected_blocks": 200
  },
  {
    "account_id": "contract.bartalamew.betanet",
    "public_key": "ed25519:7BrL86zft61Eg5D3DhZsqmSgnhg6FwzRw35Kwf2ErhpT",
    "is_slashed": false,
    "stake": "125845321889412124476457612808",
    "shards": [
      0
    ],
    "num_produced_blocks": 199,
    "num_expected_blocks": 200
  },
  {
    "account_id": "contract.nats.betanet",
    "public_key": "ed25519:CRARN6YccZCC43uacfpWGQ94u6mW4XwuGeqFAZSMaeuS",
    "is_slashed": false,
    "stake": "112014816205423954778245611898",
    "shards": [
      0
    ],
    "num_produced_blocks": 198,
    "num_expected_blocks": 200
  },
  {
    "account_id": "cryp",
    "public_key": "ed25519:7XZfMnhLqe8cPhiB2RjA6FNt75d2QpmwArSfLuNEp6dn",
    "is_slashed": false,
    "stake": "99293975609050680271419902533",
    "shards": [
      0
    ],
    "num_produced_blocks": 99,
    "num_expected_blocks": 100
  },
  {
    "account_id": "crypto-solutions.stakehouse.betanet",
    "public_key": "ed25519:FwW88Jk71HavGw2AJe6HaV2VT835idJfErrhUoK8MCyi",
    "is_slashed": false,
    "stake": "252545694684299676033588506353",
    "shards": [
      0
    ],
    "num_produced_blocks": 500,
    "num_expected_blocks": 502
  },
  {
    "account_id": "delphidigital.stakehouse.betanet",
    "public_key": "ed25519:FGB2LbogcwgXrK5eDbcJNGLsTUPbzmsWDeR6dBtJ5eLX",
    "is_slashed": false,
    "stake": "87556203381546036336311724830",
    "shards": [
      0
    ],
    "num_produced_blocks": 101,
    "num_expected_blocks": 101
  },
  {
    "account_id": "emilia.stakehouse.betanet",
    "public_key": "ed25519:AmHFyasXXqbDDPdJsW83VLdfq4xxsdCqESeLJCuPfrzx",
    "is_slashed": false,
    "stake": "141938007219364801068629062319",
    "shards": [
      0
    ],
    "num_produced_blocks": 199,
    "num_expected_blocks": 200
  },
  {
    "account_id": "enterpool.stakehouse.betanet",
    "public_key": "ed25519:4YMVzQR6PtQPLw93sFfoUGhfecihagH5ZD3R5Vf2kTQi",
    "is_slashed": false,
    "stake": "83594628121470657518074328556",
    "shards": [
      0
    ],
    "num_produced_blocks": 98,
    "num_expected_blocks": 100
  },
  {
    "account_id": "filippova_pool.stakehouse.betanet",
    "public_key": "ed25519:BRMMUk8QVR96AWXCxLyD78RQ45tazsY42ykzU1rRvuwC",
    "is_slashed": false,
    "stake": "97021652752412843956115057981",
    "shards": [
      0
    ],
    "num_produced_blocks": 98,
    "num_expected_blocks": 100
  },
  {
    "account_id": "fredrik_pool",
    "public_key": "ed25519:812BZ452dc5TYnK3SuVBzDWBahG5fRobST36acHVhHK5",
    "is_slashed": false,
    "stake": "163772467146573073469346826916",
    "shards": [
      0
    ],
    "num_produced_blocks": 0,
    "num_expected_blocks": 300
  },
  {
    "account_id": "gems",
    "public_key": "ed25519:84UPBh7a8z2CMEy6HmJFAphfQfdMGcXoukNeoNgTVnFM",
    "is_slashed": false,
    "stake": "141388397630903169551196441492",
    "shards": [
      0
    ],
    "num_produced_blocks": 198,
    "num_expected_blocks": 200
  },
  {
    "account_id": "genesislab.stakehouse.betanet",
    "public_key": "ed25519:32UigDG8e4mWr4erBVb73C5uwuDFK92AmsMn16hGy1ke",
    "is_slashed": false,
    "stake": "70144529904435473348003050803",
    "shards": [
      0
    ],
    "num_produced_blocks": 100,
    "num_expected_blocks": 100
  },
  {
    "account_id": "kazan-pool.stakehouse.betanet",
    "public_key": "ed25519:evTMDLpKoRu4pgLsxjtgLpWmPhjeStrj3x7V3vPTPFF",
    "is_slashed": false,
    "stake": "89325364061609913470337417449",
    "shards": [
      0
    ],
    "num_produced_blocks": 98,
    "num_expected_blocks": 100
  },
  {
    "account_id": "majlovesreg.stakehouse.betanet",
    "public_key": "ed25519:4FHWsrot3qivR7EieF16pKknnF1j4eaRHdLWoshRdF51",
    "is_slashed": false,
    "stake": "127647786937705823316160570608",
    "shards": [
      0
    ],
    "num_produced_blocks": 184,
    "num_expected_blocks": 200
  },
  {
    "account_id": "mort1.mort.betanet",
    "public_key": "ed25519:BeBgv9LuPThR8ScH3VQbV2KqwJ3TWfCNL2TR43XC6f49",
    "is_slashed": false,
    "stake": "154572045994260853220378471745",
    "shards": [
      0
    ],
    "num_produced_blocks": 300,
    "num_expected_blocks": 300
  },
  {
    "account_id": "nearmars.stakehouse.betanet",
    "public_key": "ed25519:4RueMT8L5cy55FJGKMktSdguF9PU2u4S54cQXX63bi5g",
    "is_slashed": false,
    "stake": "88430350911899552192343071231",
    "shards": [
      0
    ],
    "num_produced_blocks": 98,
    "num_expected_blocks": 100
  },
  {
    "account_id": "olaiolsen",
    "public_key": "ed25519:sT5iqZ3WeFMKQx7sjcak4NnKBS3fKdLY2kAwzWi2uVP",
    "is_slashed": false,
    "stake": "167200101913529326147902127019",
    "shards": [
      0
    ],
    "num_produced_blocks": 0,
    "num_expected_blocks": 301
  },
  {
    "account_id": "oligarr",
    "public_key": "ed25519:HqksthhKWmjAaiMLntcMz334TcdaADEWTQYoSYdtUrYs",
    "is_slashed": false,
    "stake": "161282436963096280520628126756",
    "shards": [
      0
    ],
    "num_produced_blocks": 0,
    "num_expected_blocks": 301
  },
  {
    "account_id": "ou812.stakehouse.betanet",
    "public_key": "ed25519:GbYBkPoR4vPq1etnXNKfxKZX6NjxL8P9Z9r7zJPnGoRG",
    "is_slashed": false,
    "stake": "140536725304705543669630474676",
    "shards": [
      0
    ],
    "num_produced_blocks": 200,
    "num_expected_blocks": 200
  },
  {
    "account_id": "plex2",
    "public_key": "ed25519:6qQ4kCneSDGumfQSZLRiFag34KypP9cmS5AYNKBUq22M",
    "is_slashed": false,
    "stake": "188975329055689089323471427051",
    "shards": [
      0
    ],
    "num_produced_blocks": 300,
    "num_expected_blocks": 301
  },
  {
    "account_id": "pool.bibiwang.betanet",
    "public_key": "ed25519:GWzkWkPJCyQPsHNtxoaU85anaatXyApqJe7S5G3jKZ19",
    "is_slashed": false,
    "stake": "73284930230127064523651653709",
    "shards": [
      0
    ],
    "num_produced_blocks": 0,
    "num_expected_blocks": 100
  },
  {
    "account_id": "pool.easy2stake.betanet",
    "public_key": "ed25519:7MTvEDcGnf99VGcSKGE7DemT8NrJTbyb4BVWrfiHq8pe",
    "is_slashed": false,
    "stake": "159540114310831681124141709237",
    "shards": [
      0
    ],
    "num_produced_blocks": 298,
    "num_expected_blocks": 301
  },
  {
    "account_id": "pool.everstake.betanet",
    "public_key": "ed25519:9GpbeWAAV9Uopg8wQ48C6TTZH8etVSQzEPbKRsns2WDH",
    "is_slashed": false,
    "stake": "127181919182781501651238044288",
    "shards": [
      0
    ],
    "num_produced_blocks": 200,
    "num_expected_blocks": 200
  },
  {
    "account_id": "pool.happin.betanet",
    "public_key": "ed25519:J3a6BLB95vy2SojeYv9Ze1e3Aj4EFZqNneejUmKPtU2s",
    "is_slashed": false,
    "stake": "162838259757185656976062959268",
    "shards": [
      0
    ],
    "num_produced_blocks": 300,
    "num_expected_blocks": 300
  },
  {
    "account_id": "pool.ryabina_io.betanet",
    "public_key": "ed25519:BnKdzGLfiAHxvXZPZ5bPM2e5oeFp5NPCFREi9zXZ7ZGe",
    "is_slashed": false,
    "stake": "118792454004520696084589263352",
    "shards": [
      0
    ],
    "num_produced_blocks": 0,
    "num_expected_blocks": 201
  },
  {
    "account_id": "pro.stakehouse.betanet",
    "public_key": "ed25519:6VGREgEwSEYqb2qbhjK8PvJc2NJKtdD9zy6RTbAccH3S",
    "is_slashed": false,
    "stake": "162453446227191624017272245284",
    "shards": [
      0
    ],
    "num_produced_blocks": 301,
    "num_expected_blocks": 301
  },
  {
    "account_id": "sam.stakehouse.betanet",
    "public_key": "ed25519:2CCBtMdhjRXTAtqg2ZtvfeDKRxKbLWp3xueMAqUk7siq",
    "is_slashed": false,
    "stake": "142722122499576223675713922687",
    "shards": [
      0
    ],
    "num_produced_blocks": 199,
    "num_expected_blocks": 200
  },
  {
    "account_id": "savelev.stakehouse.betanet",
    "public_key": "ed25519:GV1sFYApabHp4X2J3m6emPiipcQTcvfhten7ayA8CHN",
    "is_slashed": false,
    "stake": "52993282394112618427589061238",
    "shards": [
      0
    ],
    "num_produced_blocks": 98,
    "num_expected_blocks": 100
  },
  {
    "account_id": "sfpool",
    "public_key": "ed25519:HM8Rhkm3rnijhaVjfArc5G1fBiDRTW9tFeoZW5umrpxw",
    "is_slashed": false,
    "stake": "170595002877673663143347014647",
    "shards": [
      0
    ],
    "num_produced_blocks": 299,
    "num_expected_blocks": 300
  },
  {
    "account_id": "staked.stakehouse.betanet",
    "public_key": "ed25519:ARnmpTRnZD1HNKmHcDVw9CrYPTH9rNSZ4D5c9Cz3EF4C",
    "is_slashed": false,
    "stake": "181277241742515213175623474957",
    "shards": [
      0
    ],
    "num_produced_blocks": 299,
    "num_expected_blocks": 301
  },
  {
    "account_id": "starlink-pool.stakehouse.betanet",
    "public_key": "ed25519:BM8EQus1N9Q3MffKzJ8dbPfwpQcgjnB1oxSJMjetXaZZ",
    "is_slashed": false,
    "stake": "157434512091380538533896449085",
    "shards": [
      0
    ],
    "num_produced_blocks": 283,
    "num_expected_blocks": 300
  },
  {
    "account_id": "sub.rosalessierra91.betanet",
    "public_key": "ed25519:KnW54XL321MJ3GG3ZmpiNnmaWB4xEgpipeywGNHU4wY",
    "is_slashed": false,
    "stake": "141190807310889340035331661806",
    "shards": [
      0
    ],
    "num_produced_blocks": 198,
    "num_expected_blocks": 200
  },
  {
    "account_id": "sub1.crazylandd.betanet",
    "public_key": "ed25519:6rDtG4qwfbogEiQNEE18ovsWPh8WJxAkLLGK3UUNLRNF",
    "is_slashed": false,
    "stake": "159274213715245108302250675093",
    "shards": [
      0
    ],
    "num_produced_blocks": 300,
    "num_expected_blocks": 301
  },
  {
    "account_id": "sub2.balinode.betanet",
    "public_key": "ed25519:Bq3VjhejNpVFwYj4Lip6UWK2X2GvmdKniGJBPUWB4a5Q",
    "is_slashed": false,
    "stake": "91427998493519164401893605459",
    "shards": [
      0
    ],
    "num_produced_blocks": 101,
    "num_expected_blocks": 101
  },
  {
    "account_id": "swain2.stakehouse.betanet",
    "public_key": "ed25519:87a9R8upfghCz16upDkq9ekXiG8eKNDaCKD6bd43pGjT",
    "is_slashed": false,
    "stake": "139880111545221054252244934966",
    "shards": [
      0
    ],
    "num_produced_blocks": 197,
    "num_expected_blocks": 200
  },
  {
    "account_id": "tatianka",
    "public_key": "ed25519:7meqkoLMXro7bAD3mmBWMzZ3Ski98Z6V8YpDvdFLAYWP",
    "is_slashed": false,
    "stake": "133485958737673076824731365549",
    "shards": [
      0
    ],
    "num_produced_blocks": 196,
    "num_expected_blocks": 200
  },
  {
    "account_id": "tommywesley",
    "public_key": "ed25519:EZS7dMdmoDDmr6nKHuSx1aDrdvQQagsrsjEPStMV1yUe",
    "is_slashed": false,
    "stake": "156022269438046388836151733356",
    "shards": [
      0
    ],
    "num_produced_blocks": 0,
    "num_expected_blocks": 302
  },
  {
    "account_id": "validator.projecttent.betanet",
    "public_key": "ed25519:4BFtRDYju4vtVzgtmUev4uEHyo52syQWM4wvkcQggYT8",
    "is_slashed": false,
    "stake": "140702117787447878258761162946",
    "shards": [
      0
    ],
    "num_produced_blocks": 200,
    "num_expected_blocks": 200
  },
  {
    "account_id": "validator_italia_contract",
    "public_key": "ed25519:HkchASewGKi7cHiif44mtB1xd3oxyxsNGd8sLgemKybP",
    "is_slashed": false,
    "stake": "154477419185770725857607030123",
    "shards": [
      0
    ],
    "num_produced_blocks": 298,
    "num_expected_blocks": 300
  },
  {
    "account_id": "vipstakes",
    "public_key": "ed25519:DmSyLLRR8zjCUiYNz8PRBQtmE4HbLVrzFoDJSk6zT9AK",
    "is_slashed": false,
    "stake": "111840415887618174745353743768",
    "shards": [
      0
    ],
    "num_produced_blocks": 0,
    "num_expected_blocks": 200
  },
  {
    "account_id": "volvos60909",
    "public_key": "ed25519:FLXP138XEfB7WRf9BS1NgpqzBnHWJbPqbReuB4wASxz3",
    "is_slashed": false,
    "stake": "158592910355482998173864057212",
    "shards": [
      0
    ],
    "num_produced_blocks": 297,
    "num_expected_blocks": 300
  }
]