[
  {
    "account_id": "31337x.31337.betanet",
    "public_key": "ed25519:J3yfHuxL17utu8C9SS9XWo3q6dEkMU9BG2JtFDmKvimb",
    "is_slashed": false,
    "stake": "59256602475267671172296674207",
    "shards": [
      0
    ],
    "num_produced_blocks": 100,
    "num_expected_blocks": 100
  },
  {
    "account_id": "ag_staking",
    "public_key": "ed25519:5RFyRfrUetiG4bxmWKtRqbXtDtT2acngUBZYrCXk2Mja",
    "is_slashed": false,
    "stake": "215741371305567191791589774526",
    "shards": [
      0
    ],
    "num_produced_blocks": 400,
    "num_expected_blocks": 400
  },
  {
    "account_id": "aptemuyc4",
    "public_key": "ed25519:Dzcdmjxo6wqD8vHgxkGM7wccXrxcWpCpZ6JzrPvr5KZy",
    "is_slashed": false,
    "stake": "121340745750711697156576651348",
    "shards": [
      0
    ],
    "num_produced_blocks": 0,
    "num_expected_blocks": 200
  },
  {
    "account_id": "audit_two.stakehouse.betanet",
    "public_key": "ed25519:D38NhZDdmSh5CFkCaPHBfZGvsC5aiQVmvH27eqMuYpmt",
    "is_slashed": false,
    "stake": "59257536113375682204747375445",
    "shards": [
      0
    ],
    "num_produced_blocks": 100,
    "num_expected_blocks": 100
  },
  {
    "account_id": "awesome",
    "public_key": "ed25519:AVb1yZULrZ117PHMynbZnUWdkanesudUYKAAMEeaSVk8",
    "is_slashed": false,
    "stake": "94286813571151235373143736815",
    "shards": [
      0
    ],
    "num_produced_blocks": 98,
    "num_expected_blocks": 100
  },
  {
    "account_id": "bucket",
    "public_key": "ed25519:6TCBt4yLU6m4KKPPiVX9NumZuHEB5aPcNRJoLrUecg4w",
    "is_slashed": false,
    "stake": "132612765858932009983782632233",
    "shards": [
      0
    ],
    "num_produced_blocks": 0,
    "num_expected_blocks": 200
  },
  {
    "account_id": "c1.hashquark",
    "public_key": "ed25519:8zohSr8u46tHfGuP8Y9fp5Gu2h4CdtCJPeSHSHSjZta",
    "is_slashed": false,
    "stake": "82999190811681910819447308268",
    "shards": [
      0
    ],
    "num_produced_blocks": 100,
    "num_expected_blocks": 100
  },
  {
    "account_id": "contract.bartalamew.betanet",
    "public_key": "ed25519:7BrL86zft61Eg5D3DhZsqmSgnhg6FwzRw35Kwf2ErhpT",
    "is_slashed": false,
    "stake": "128114676759654155293321088993",
    "shards": [
      0
    ],
    "num_produced_blocks": 172,
    "num_expected_blocks": 200
  },
  {
    "account_id": "contract.nats.betanet",
    "public_key": "ed25519:CRARN6YccZCC43uacfpWGQ94u6mW4XwuGeqFAZSMaeuS",
    "is_slashed": false,
    "stake": "127928592384639210851989483120",
    "shards": [
      0
    ],
    "num_produced_blocks": 200,
    "num_expected_blocks": 200
  },
  {
    "account_id": "coolpool.dimaro1.betanet",
    "public_key": "ed25519:3kRXSgd3QbsmBrptDKUqJ3o5CrXEenbPLSoqPrXzRhk9",
    "is_slashed": false,
    "stake": "135650603867757320731104369790",
    "shards": [
      0
    ],
    "num_produced_blocks": 200,
    "num_expected_blocks": 200
  },
  {
    "account_id": "cryp",
    "public_key": "ed25519:7XZfMnhLqe8cPhiB2RjA6FNt75d2QpmwArSfLuNEp6dn",
    "is_slashed": false,
    "stake": "129352579268868617294573067362",
    "shards": [
      0
    ],
    "num_produced_blocks": 199,
    "num_expected_blocks": 200
  },
  {
    "account_id": "delight_pool",
    "public_key": "ed25519:6XDV4Q4HZPFNdsmc2g8b77MSp19pbooeSSsdufupXRKH",
    "is_slashed": false,
    "stake": "115683632657928769178499757441",
    "shards": [
      0
    ],
    "num_produced_blocks": 200,
    "num_expected_blocks": 200
  },
  {
    "account_id": "delphidigital.stakehouse.betanet",
    "public_key": "ed25519:FGB2LbogcwgXrK5eDbcJNGLsTUPbzmsWDeR6dBtJ5eLX",
    "is_slashed": false,
    "stake": "118417577518279640857503385377",
    "shards": [
      0
    ],
    "num_produced_blocks": 200,
    "num_expected_blocks": 200
  },
  {
    "account_id": "dog.bears.betanet",
    "public_key": "ed25519:8x2zfo7QksoJ77iLEkYHzhvQnUAJ97WCC7BijWUDfe3N",
    "is_slashed": false,
    "stake": "114405757305356834783636124243",
    "shards": [
      0
    ],
    "num_produced_blocks": 200,
    "num_expected_blocks": 200
  },
  {
    "account_id": "enterpool.stakehouse.betanet",
    "public_key": "ed25519:4YMVzQR6PtQPLw93sFfoUGhfecihagH5ZD3R5Vf2kTQi",
    "is_slashed": false,
    "stake": "93715570643482045230529209525",
    "shards": [
      0
    ],
    "num_produced_blocks": 0,
    "num_expected_blocks": 100
  },
  {
    "account_id": "filippova_pool.stakehouse.betanet",
    "public_key": "ed25519:BRMMUk8QVR96AWXCxLyD78RQ45tazsY42ykzU1rRvuwC",
    "is_slashed": false,
    "stake": "132332565107565468179869900000",
    "shards": [
      0
    ],
    "num_produced_blocks": 200,
    "num_expected_blocks": 200
  },
  {
    "account_id": "forbole.stakehouse.betanet",
    "public_key": "ed25519:4hfJ1WWZDbGNScaHAmjGpZRVfn5mi1qaqNcGixaW94Qn",
    "is_slashed": false,
    "stake": "128803497018922396649686046790",
    "shards": [
      0
    ],
    "num_produced_blocks": 200,
    "num_expected_blocks": 200
  },
  {
    "account_id": "gems",
    "public_key": "ed25519:84UPBh7a8z2CMEy6HmJFAphfQfdMGcXoukNeoNgTVnFM",
    "is_slashed": false,
    "stake": "183786222593117962157498803567",
    "shards": [
      0
    ],
    "num_produced_blocks": 300,
    "num_expected_blocks": 300
  },
  {
    "account_id": "genesislab.stakehouse.betanet",
    "public_key": "ed25519:32UigDG8e4mWr4erBVb73C5uwuDFK92AmsMn16hGy1ke",
    "is_slashed": false,
    "stake": "93920762803925828327109307416",
    "shards": [
      0
    ],
    "num_produced_blocks": 100,
    "num_expected_blocks": 100
  },
  {
    "account_id": "mort1.mort.betanet",
    "public_key": "ed25519:BeBgv9LuPThR8ScH3VQbV2KqwJ3TWfCNL2TR43XC6f49",
    "is_slashed": false,
    "stake": "208853312103078958693932453848",
    "shards": [
      0
    ],
    "num_produced_blocks": 300,
    "num_expected_blocks": 300
  },
  {
    "account_id": "nearmars.stakehouse.betanet",
    "public_key": "ed25519:4RueMT8L5cy55FJGKMktSdguF9PU2u4S54cQXX63bi5g",
    "is_slashed": false,
    "stake": "116781479542051875266419779406",
    "shards": [
      0
    ],
    "num_produced_blocks": 200,
    "num_expected_blocks": 200
  },
  {
    "account_id": "plex2",
    "public_key": "ed25519:6qQ4kCneSDGumfQSZLRiFag34KypP9cmS5AYNKBUq22M",
    "is_slashed": false,
    "stake": "258387899969467958292190165591",
    "shards": [
      0
    ],
    "num_produced_blocks": 392,
    "num_expected_blocks": 400
  },
  {
    "account_id": "pool.easy2stake.betanet",
    "public_key": "ed25519:7MTvEDcGnf99VGcSKGE7DemT8NrJTbyb4BVWrfiHq8pe",
    "is_slashed": false,
    "stake": "194310423348406315815964040556",
    "shards": [
      0
    ],
    "num_produced_blocks": 297,
    "num_expected_blocks": 300
  },
  {
    "account_id": "pool.everstake.betanet",
    "public_key": "ed25519:9GpbeWAAV9Uopg8wQ48C6TTZH8etVSQzEPbKRsns2WDH",
    "is_slashed": false,
    "stake": "173909121943550077966099389445",
    "shards": [
      0
    ],
    "num_produced_blocks": 300,
    "num_expected_blocks": 300
  },
  {
    "account_id": "pool.ryabina_io.betanet",
    "public_key": "ed25519:BnKdzGLfiAHxvXZPZ5bPM2e5oeFp5NPCFREi9zXZ7ZGe",
    "is_slashed": false,
    "stake": "118792490620849642560351352653",
    "shards": [
      0
    ],
    "num_produced_blocks": 0,
    "num_expected_blocks": 200
  },
  {
    "account_id": "pro.stakehouse.betanet",
    "public_key": "ed25519:6VGREgEwSEYqb2qbhjK8PvJc2NJKtdD9zy6RTbAccH3S",
    "is_slashed": false,
    "stake": "214215559717634135627711411670",
    "shards": [
      0
    ],
    "num_produced_blocks": 300,
    "num_expected_blocks": 300
  },
  {
    "account_id": "rioblocks.stakehouse.betanet",
    "public_key": "ed25519:8jAk7n34DSaJYY1N1MwTqn8ARRTWTTaadhzqVSkgoSwi",
    "is_slashed": false,
    "stake": "168473144470788447976975505074",
    "shards": [
      0
    ],
    "num_produced_blocks": 300,
    "num_expected_blocks": 300
  },
  {
    "account_id": "savelev.stakehouse.betanet",
    "public_key": "ed25519:GV1sFYApabHp4X2J3m6emPiipcQTcvfhten7ayA8CHN",
    "is_slashed": false,
    "stake": "59581632020177999583670568847",
    "shards": [
      0
    ],
    "num_produced_blocks": 100,
    "num_expected_blocks": 100
  },
  {
    "account_id": "sc.foxnorth1210.betanet",
    "public_key": "ed25519:6bBbJBccu1i9rbdPuMpoyewyChimhpPVu2kUnW82yBa7",
    "is_slashed": false,
    "stake": "146219403520943148951275200488",
    "shards": [
      0
    ],
    "num_produced_blocks": 199,
    "num_expected_blocks": 200
  },
  {
    "account_id": "sc.galbraith.betanet",
    "public_key": "ed25519:G9ztYhuN8Lc8Dr9nk5wta9ZTwuSoM1fEJip3qsdMTNvP",
    "is_slashed": false,
    "stake": "183122137789646541940171860109",
    "shards": [
      0
    ],
    "num_produced_blocks": 300,
    "num_expected_blocks": 300
  },
  {
    "account_id": "sfpool",
    "public_key": "ed25519:HM8Rhkm3rnijhaVjfArc5G1fBiDRTW9tFeoZW5umrpxw",
    "is_slashed": false,
    "stake": "232180734160440149273266541627",
    "shards": [
      0
    ],
    "num_produced_blocks": 400,
    "num_expected_blocks": 400
  },
  {
    "account_id": "sl1sub",
    "public_key": "ed25519:EGCw1rG1LhVqRByDqiT7PC7QFwgrSMoP5PXTwDhrJXkb",
    "is_slashed": false,
    "stake": "149418350801872669932422277646",
    "shards": [
      0
    ],
    "num_produced_blocks": 200,
    "num_expected_blocks": 200
  },
  {
    "account_id": "staked.stakehouse.betanet",
    "public_key": "ed25519:ARnmpTRnZD1HNKmHcDVw9CrYPTH9rNSZ4D5c9Cz3EF4C",
    "is_slashed": false,
    "stake": "247477049629800377933352387245",
    "shards": [
      0
    ],
    "num_produced_blocks": 400,
    "num_expected_blocks": 400
  },
  {
    "account_id": "starlink-pool.stakehouse.betanet",
    "public_key": "ed25519:BM8EQus1N9Q3MffKzJ8dbPfwpQcgjnB1oxSJMjetXaZZ",
    "is_slashed": false,
    "stake": "208409669714438029895353250469",
    "shards": [
      0
    ],
    "num_produced_blocks": 300,
    "num_expected_blocks": 300
  },
  {
    "account_id": "sub.rosalessierra91.betanet",
    "public_key": "ed25519:KnW54XL321MJ3GG3ZmpiNnmaWB4xEgpipeywGNHU4wY",
    "is_slashed": false,
    "stake": "191333378149197812740588315669",
    "shards": [
      0
    ],
    "num_produced_blocks": 299,
    "num_expected_blocks": 300
  },
  {
    "account_id": "sub1.crazylandd.betanet",
    "public_key": "ed25519:6rDtG4qwfbogEiQNEE18ovsWPh8WJxAkLLGK3UUNLRNF",
    "is_slashed": false,
    "stake": "217843073896480734982626914044",
    "shards": [
      0
    ],
    "num_produced_blocks": 400,
    "num_expected_blocks": 400
  },
  {
    "account_id": "sub2.balinode.betanet",
    "public_key": "ed25519:Bq3VjhejNpVFwYj4Lip6UWK2X2GvmdKniGJBPUWB4a5Q",
    "is_slashed": false,
    "stake": "122668111487967240593569982576",
    "shards": [
      0
    ],
    "num_produced_blocks": 200,
    "num_expected_blocks": 200
  },
  {
    "account_id": "tribe-pool.stakehouse.betanet",
    "public_key": "ed25519:6zmpAstbbb9cBcwE6MWU1Vy3umCjQ7kRmzLsM56nyv8",
    "is_slashed": false,
    "stake": "92983379807794565836770064677",
    "shards": [
      0
    ],
    "num_produced_blocks": 100,
    "num_expected_blocks": 100
  },
  {
    "account_id": "validator.projecttent.betanet",
    "public_key": "ed25519:4BFtRDYju4vtVzgtmUev4uEHyo52syQWM4wvkcQggYT8",
    "is_slashed": false,
    "stake": "161541933012587534832052377285",
    "shards": [
      0
    ],
    "num_produced_blocks": 300,
    "num_expected_blocks": 300
  },
  {
    "account_id": "validator_italia_contract",
    "public_key": "ed25519:HkchASewGKi7cHiif44mtB1xd3oxyxsNGd8sLgemKybP",
    "is_slashed": false,
    "stake": "327067867382899320651302415352",
    "shards": [
      0
    ],
    "num_produced_blocks": 599,
    "num_expected_blocks": 600
  },
  {
    "account_id": "volvos60909",
    "public_key": "ed25519:FLXP138XEfB7WRf9BS1NgpqzBnHWJbPqbReuB4wASxz3",
    "is_slashed": false,
    "stake": "216280649883939265076765559745",
    "shards": [
      0
    ],
    "num_produced_blocks": 400,
    "num_expected_blocks": 400
  }
]