[
  {
    "account_id": "01node.poolv1.near",
    "public_key": "ed25519:5xz7EbcnPqabwoFezdJBxieK8S7XLsdHHuLwM4vLLhFt",
    "is_slashed": false,
    "stake": "3552178399094676904581502478415",
    "shards": [
      0
    ],
    "num_produced_blocks": 432,
    "num_expected_blocks": 432
  },
  {
    "account_id": "08investinwomen_runbybisontrails.poolv1.near",
    "public_key": "ed25519:C6yqxQ3suwjmm8ufG5e3BsHiwxUs9h839FCneF41V7TM",
    "is_slashed": false,
    "stake": "2580734857540173489564358049010",
    "shards": [
      0
    ],
    "num_produced_blocks": 432,
    "num_expected_blocks": 432
  },
  {
    "account_id": "abl_pool.poolv1.near",
    "public_key": "ed25519:5nnwJr7WgMXbWiudFcen9AMXRUXWA3ij6GGFZvRWXA3C",
    "is_slashed": false,
    "stake": "4531685606162508734647934813972",
    "shards": [
      0
    ],
    "num_produced_blocks": 864,
    "num_expected_blocks": 864
  },
  {
    "account_id": "accomplice.poolv1.near",
    "public_key": "ed25519:5ck255MtkoGQxh9LfjNtdb4M7WHkUmjU7SBJCEkZP2B7",
    "is_slashed": false,
    "stake": "5297297316050564319810976473130",
    "shards": [
      0
    ],
    "num_produced_blocks": 864,
    "num_expected_blocks": 864
  },
  {
    "account_id": "alex.poolv1.near",
    "public_key": "ed25519:5BVKQ5zZKtEUM3AHgj6KAerTpuh3CVZHtAbmVfxLbLhc",
    "is_slashed": false,
    "stake": "3019127170427839667980026296958",
    "shards": [
      0
    ],
    "num_produced_blocks": 0,
    "num_expected_blocks": 432
  },
  {
    "account_id": "anonymous.poolv1.near",
    "public_key": "ed25519:Hoj7LbPwNwAkLFhf8z2aDF1BG6NDSrq1BfkdaKqPfbXx",
    "is_slashed": false,
    "stake": "6400850846351234973446777013800",
    "shards": [
      0
    ],
    "num_produced_blocks": 864,
    "num_expected_blocks": 864
  },
  {
    "account_id": "appload.poolv1.near",
    "public_key": "ed25519:6LbMVL6otkvZbpuC9sN3z7EXSMo3PT9noPeBdBZTFneM",
    "is_slashed": false,
    "stake": "3872243677518528863572551211316",
    "shards": [
      0
    ],
    "num_produced_blocks": 432,
    "num_expected_blocks": 432
  },
  {
    "account_id": "artemis.poolv1.near",
    "public_key": "ed25519:EP6NE3GzNBK6qoXoT82JB9NnuUJeNZeuwXPuGRazrqJP",
    "is_slashed": false,
    "stake": "3051199537338442763088330632889",
    "shards": [
      0
    ],
    "num_produced_blocks": 432,
    "num_expected_blocks": 432
  },
  {
    "account_id": "ashert.poolv1.near",
    "public_key": "ed25519:7zqCoSG1i7yBHwKNaqL3CZSdnXq2bjFutXZUWUy3eUUB",
    "is_slashed": false,
    "stake": "2688056569149479043003248116857",
    "shards": [
      0
    ],
    "num_produced_blocks": 432,
    "num_expected_blocks": 432
  },
  {
    "account_id": "astro-stakers.poolv1.near",
    "public_key": "ed25519:2nPSBCzjqikgwrqUMcuEVReJhmkC91eqJGPGqH9sZc28",
    "is_slashed": false,
    "stake": "10429535115772596398422170836911",
    "shards": [
      0
    ],
    "num_produced_blocks": 1728,
    "num_expected_blocks": 1728
  },
  {
    "account_id": "audit_one.poolv1.near",
    "public_key": "ed25519:9x2LqdGVL8MKbAziezMhQjPCKKeFAaExeyJpVvBvGuAC",
    "is_slashed": false,
    "stake": "3021428919993769840185802745194",
    "shards": [
      0
    ],
    "num_produced_blocks": 431,
    "num_expected_blocks": 432
  },
  {
    "account_id": "baziliknear.poolv1.near",
    "public_key": "ed25519:E4LAWdgLifBEoaWvhRNy5vpdAnUc3GsUHePeiAurZY5v",
    "is_slashed": false,
    "stake": "4442828619579250341069663597220",
    "shards": [
      0
    ],
    "num_produced_blocks": 432,
    "num_expected_blocks": 432
  },
  {
    "account_id": "bisontrails.poolv1.near",
    "public_key": "ed25519:Emk6wQJtpQZRJCvvPmmwP9GD2Pk37xxRpmb5uRvJpX62",
    "is_slashed": false,
    "stake": "9240917964134026630602893230590",
    "shards": [
      0
    ],
    "num_produced_blocks": 1728,
    "num_expected_blocks": 1728
  },
  {
    "account_id": "buildlinks.poolv1.near",
    "public_key": "ed25519:Hd3irGt4zEqRPAzcFszX3oTkVWRFFxdecDvShCJSS1Wg",
    "is_slashed": false,
    "stake": "5189875941414628206768947248529",
    "shards": [
      0
    ],
    "num_produced_blocks": 864,
    "num_expected_blocks": 864
  },
  {
    "account_id": "certusone.poolv1.near",
    "public_key": "ed25519:4kwUVNSZ61BT3xbc1fL718UP2RqgvMa5aAYBaoav1wvk",
    "is_slashed": false,
    "stake": "3775895096229604035623904285645",
    "shards": [
      0
    ],
    "num_produced_blocks": 432,
    "num_expected_blocks": 432
  },
  {
    "account_id": "chorusone.poolv1.near",
    "public_key": "ed25519:AZwJAgu2qRxHwdpj8ioZEFGcc2jbaZGN7ZvUe7CuXtM7",
    "is_slashed": false,
    "stake": "6163553276697273797360792011238",
    "shards": [
      0
    ],
    "num_produced_blocks": 864,
    "num_expected_blocks": 864
  },
  {
    "account_id": "cryptium.poolv1.near",
    "public_key": "ed25519:5Y9hW8cKBb5RnsJBqttHHC5ujz5zcZZ5xnrJPwkCWmGQ",
    "is_slashed": false,
    "stake": "13117353609796903580971420478282",
    "shards": [
      0
    ],
    "num_produced_blocks": 2160,
    "num_expected_blocks": 2160
  },
  {
    "account_id": "d1.poolv1.near",
    "public_key": "ed25519:7ZhMRwnSHGJtWjGBZiRhhSi6XyqKeNHtnEXsVTNdrsk6",
    "is_slashed": false,
    "stake": "7595437078933127960102539731647",
    "shards": [
      0
    ],
    "num_produced_blocks": 1296,
    "num_expected_blocks": 1296
  },
  {
    "account_id": "dokiacapital.poolv1.near",
    "public_key": "ed25519:FGcJJeWMyx1xDbfkcPM2oMeUeGaADJuPmeqx5rjsHn7t",
    "is_slashed": false,
    "stake": "5953193252698430580351567171871",
    "shards": [
      0
    ],
    "num_produced_blocks": 864,
    "num_expected_blocks": 864
  },
  {
    "account_id": "dsrvlabs.poolv1.near",
    "public_key": "ed25519:9SACdsDDgXA2WZLfJvpkKbu22Exxtc4CMbeHmVnN2P4a",
    "is_slashed": false,
    "stake": "4707798458406665887447678607399",
    "shards": [
      0
    ],
    "num_produced_blocks": 864,
    "num_expected_blocks": 864
  },
  {
    "account_id": "electric.poolv1.near",
    "public_key": "ed25519:GpSr5KAZMZ1Cb4dHMRUVhmp95y2fmWtm4dEjAr8iAva5",
    "is_slashed": false,
    "stake": "3444696247339426300769326231939",
    "shards": [
      0
    ],
    "num_produced_blocks": 432,
    "num_expected_blocks": 432
  },
  {
    "account_id": "epic.poolv1.near",
    "public_key": "ed25519:68HExKDtw1CjGzopZ8fMAMhMSZRVKRhwLzLQmGKtFNzT",
    "is_slashed": false,
    "stake": "7291976160458944149591172687078",
    "shards": [
      0
    ],
    "num_produced_blocks": 1296,
    "num_expected_blocks": 1296
  },
  {
    "account_id": "erm.poolv1.near",
    "public_key": "ed25519:88nnN6LAuCbJaj9wucd1WUMfTtdv2s3njpvozHft8oQ5",
    "is_slashed": false,
    "stake": "3694908022156468007327132914171",
    "shards": [
      0
    ],
    "num_produced_blocks": 432,
    "num_expected_blocks": 432
  },
  {
    "account_id": "everstake.poolv1.near",
    "public_key": "ed25519:4JLvwa1r2eAxHLyKeDJnpqMG5f2Z9rr49rwuTwb9g8u2",
    "is_slashed": false,
    "stake": "5320132603933295842074757056833",
    "shards": [
      0
    ],
    "num_produced_blocks": 864,
    "num_expected_blocks": 864
  },
  {
    "account_id": "figment.poolv1.near",
    "public_key": "ed25519:7RjyY1bRKDqkshbKZtgpQdwsdxou8j9my8g1hPKZ9ngM",
    "is_slashed": false,
    "stake": "5859023460766129332045003198174",
    "shards": [
      0
    ],
    "num_produced_blocks": 864,
    "num_expected_blocks": 864
  },
  {
    "account_id": "finoa.poolv1.near",
    "public_key": "ed25519:CwTRmvNz4VJYGPe6Ngx5Rnpr9YvCXgdgKbMjsYMkicSa",
    "is_slashed": false,
    "stake": "7805003468408236278208912465375",
    "shards": [
      0
    ],
    "num_produced_blocks": 1296,
    "num_expected_blocks": 1296
  },
  {
    "account_id": "fish.poolv1.near",
    "public_key": "ed25519:27KegJd17HeXHk9h5MqkT35QAuvYvo5GFgPTpSVU4kPN",
    "is_slashed": false,
    "stake": "2463640246714277922612323580881",
    "shards": [
      0
    ],
    "num_produced_blocks": 432,
    "num_expected_blocks": 432
  },
  {
    "account_id": "fresh.poolv1.near",
    "public_key": "ed25519:6YHLXhohY8kMnkp5Jw4HrJ52xtdyt1rcP6AaWkKzh3ED",
    "is_slashed": false,
    "stake": "5711839061216370865548007889223",
    "shards": [
      0
    ],
    "num_produced_blocks": 863,
    "num_expected_blocks": 864
  },
  {
    "account_id": "hashquark.poolv1.near",
    "public_key": "ed25519:3YDdmN1vhF7yAWnYxGMHY46jcLE9h11HvEeF6Kntugeq",
    "is_slashed": false,
    "stake": "3473972933832117953994624445159",
    "shards": [
      0
    ],
    "num_produced_blocks": 432,
    "num_expected_blocks": 432
  },
  {
    "account_id": "hb436_pool.poolv1.near",
    "public_key": "ed25519:7oU4C3vWqkeup7aMfjyV1ojt7yKX7ShLfvNCahBRy1eW",
    "is_slashed": false,
    "stake": "5226409134345120442170733417273",
    "shards": [
      0
    ],
    "num_produced_blocks": 864,
    "num_expected_blocks": 864
  },
  {
    "account_id": "ideocolabventures.poolv1.near",
    "public_key": "ed25519:6NFuvrmnJiokXibR9Z7TUHjB4NJnD1rJAHhBu9JWmBdh",
    "is_slashed": false,
    "stake": "2604037014499421876055455675506",
    "shards": [
      0
    ],
    "num_produced_blocks": 432,
    "num_expected_blocks": 432
  },
  {
    "account_id": "inotel.poolv1.near",
    "public_key": "ed25519:DmEDRntb9NwfbfdvDf6wzjsw1vxzQcJAAhFL2J75iLwr",
    "is_slashed": false,
    "stake": "4485533972819122928869185278492",
    "shards": [
      0
    ],
    "num_produced_blocks": 431,
    "num_expected_blocks": 432
  },
  {
    "account_id": "jazza.poolv1.near",
    "public_key": "ed25519:EW66Fkv7XcE9FiybuYtVURjHhYeEgwWWpzF685Vi7foY",
    "is_slashed": false,
    "stake": "4721027123907030599277558017329",
    "shards": [
      0
    ],
    "num_produced_blocks": 864,
    "num_expected_blocks": 864
  },
  {
    "account_id": "jubi.poolv1.near",
    "public_key": "ed25519:4XVFgdSWjfWdPqaufazhyDZgonJMFNhz1jvTQNfgsavh",
    "is_slashed": false,
    "stake": "5265017250220497309107800765963",
    "shards": [
      0
    ],
    "num_produced_blocks": 864,
    "num_expected_blocks": 864
  },
  {
    "account_id": "lunanova.poolv1.near",
    "public_key": "ed25519:qkfP4NsSuHybdLhdvvYQ2Y9xWPsd249thEvrzbJBKNc",
    "is_slashed": false,
    "stake": "3639120064682497787357123548472",
    "shards": [
      0
    ],
    "num_produced_blocks": 432,
    "num_expected_blocks": 432
  },
  {
    "account_id": "lux.poolv1.near",
    "public_key": "ed25519:HzTGTDfTz63QGvvUdMGozFeaENFGyYAoSrqYJb23qZFN",
    "is_slashed": false,
    "stake": "4104643611707794842332644408971",
    "shards": [
      0
    ],
    "num_produced_blocks": 432,
    "num_expected_blocks": 432
  },
  {
    "account_id": "majlovesreg.poolv1.near",
    "public_key": "ed25519:DtBmPrPFZR2Zo3aUc8PkVGpnstZRLjRJpkEJJWoPGpkz",
    "is_slashed": false,
    "stake": "3003692179779417619054270498809",
    "shards": [
      0
    ],
    "num_produced_blocks": 427,
    "num_expected_blocks": 432
  },
  {
    "account_id": "masternode24.poolv1.near",
    "public_key": "ed25519:5ZyaXsGCya4Sch5bqUfohvo7iRFYB9ancRouggWRsiDU",
    "is_slashed": false,
    "stake": "3455012641319402452881766922782",
    "shards": [
      0
    ],
    "num_produced_blocks": 432,
    "num_expected_blocks": 432
  },
  {
    "account_id": "moonlet.poolv1.near",
    "public_key": "ed25519:GkDwzPckMfhkdYgyFG69Uph8RJ12BcV9xNeZW2q93ZJD",
    "is_slashed": false,
    "stake": "3021419369276958109997725149931",
    "shards": [
      0
    ],
    "num_produced_blocks": 432,
    "num_expected_blocks": 432
  },
  {
    "account_id": "near8888.poolv1.near",
    "public_key": "ed25519:5TmFjs1TFNkdN8re9JC5WUbPyt6ihkUonV1JZe2YKEw1",
    "is_slashed": false,
    "stake": "5883882275328540222408588587781",
    "shards": [
      0
    ],
    "num_produced_blocks": 863,
    "num_expected_blocks": 864
  },
  {
    "account_id": "nearfans.poolv1.near",
    "public_key": "ed25519:GM8vWM4TqTt7jh3sXYCAs2KPyn4vEmAceteBGEFYhyku",
    "is_slashed": false,
    "stake": "3081357726394841406674349398568",
    "shards": [
      0
    ],
    "num_produced_blocks": 432,
    "num_expected_blocks": 432
  },
  {
    "account_id": "nodeasy.poolv1.near",
    "public_key": "ed25519:8mjespqqUePSYSsxYxPqCUsZUuMxVJr1vjBRwFeCke5K",
    "is_slashed": false,
    "stake": "3072814360215941708195861417723",
    "shards": [
      0
    ],
    "num_produced_blocks": 432,
    "num_expected_blocks": 432
  },
  {
    "account_id": "northernlights.poolv1.near",
    "public_key": "ed25519:7HXh6iS9Rh92Uj1c5T9fPjQXPLnti4Rr2cJQcJEYpdGV",
    "is_slashed": false,
    "stake": "4528361703833188901073714184057",
    "shards": [
      0
    ],
    "num_produced_blocks": 864,
    "num_expected_blocks": 864
  },
  {
    "account_id": "openshards.poolv1.near",
    "public_key": "ed25519:4Xm73PiAGMZu3mZg4gF7j96iTAFHGbPvqzxBaTgKP4ub",
    "is_slashed": false,
    "stake": "6753931582757499043750809079457",
    "shards": [
      0
    ],
    "num_produced_blocks": 864,
    "num_expected_blocks": 864
  },
  {
    "account_id": "rekt.poolv1.near",
    "public_key": "ed25519:FoAaUdVKEHtVokG1aVmJNou61YcfQhXmaZ5Hnfsz4fHC",
    "is_slashed": false,
    "stake": "6060708332871171866688148711844",
    "shards": [
      0
    ],
    "num_produced_blocks": 864,
    "num_expected_blocks": 864
  },
  {
    "account_id": "sharpdarts.poolv1.near",
    "public_key": "ed25519:9XMHXqv7rM3QQxzjUu7dfKD7GhMkq8CEceaPdkhiBQUX",
    "is_slashed": false,
    "stake": "2515804304591949826373080414255",
    "shards": [
      0
    ],
    "num_produced_blocks": 432,
    "num_expected_blocks": 432
  },
  {
    "account_id": "smart-stake.poolv1.near",
    "public_key": "ed25519:A6wpkLQiYqPZ1rbd9s5S1Bg3LxccVsQqiCRDUXwzJ6Hx",
    "is_slashed": false,
    "stake": "3357029403244514736581900970518",
    "shards": [
      0
    ],
    "num_produced_blocks": 206,
    "num_expected_blocks": 432
  },
  {
    "account_id": "staked.poolv1.near",
    "public_key": "ed25519:3JBVXqenru2ErAM1kHQ8qfd29dCkURLd6JKrFgtmcDTZ",
    "is_slashed": false,
    "stake": "18929924610103917222415698867586",
    "shards": [
      0
    ],
    "num_produced_blocks": 3456,
    "num_expected_blocks": 3456
  },
  {
    "account_id": "stakesabai.poolv1.near",
    "public_key": "ed25519:6abauNvvWnEkagjVpWRy2tZJdzPkmqurUjteMTKk5KQF",
    "is_slashed": false,
    "stake": "4608295801119902000257695963784",
    "shards": [
      0
    ],
    "num_produced_blocks": 863,
    "num_expected_blocks": 864
  },
  {
    "account_id": "stakin.poolv1.near",
    "public_key": "ed25519:85UGfKdVoxX9u86JsBMxmVHBguYonnM3vTR2WoD5GkEg",
    "is_slashed": false,
    "stake": "4356871448260485330627583975987",
    "shards": [
      0
    ],
    "num_produced_blocks": 432,
    "num_expected_blocks": 432
  },
  {
    "account_id": "stardust.poolv1.near",
    "public_key": "ed25519:6rxCJpTnrT6NFuGg6d5Dj3FEUz1ScNU9u35ywB3dYhrX",
    "is_slashed": false,
    "stake": "7722007424908989554711332152657",
    "shards": [
      0
    ],
    "num_produced_blocks": 1296,
    "num_expected_blocks": 1296
  },
  {
    "account_id": "tottenham_hotspur.poolv1.near",
    "public_key": "ed25519:4sxapJrqPVEpnqriAkJHMjyEQ8rMXQb8T2wv5WgHLZtj",
    "is_slashed": false,
    "stake": "4232626621780113843468983330390",
    "shards": [
      0
    ],
    "num_produced_blocks": 432,
    "num_expected_blocks": 432
  },
  {
    "account_id": "zavodil.poolv1.near",
    "public_key": "ed25519:HHARoU1hANWF9hu7YRstDDvgyigBhUeUuqecRVr8dpUz",
    "is_slashed": false,
    "stake": "9371692894108882187134123651486",
    "shards": [
      0
    ],
    "num_produced_blocks": 1728,
    "num_expected_blocks": 1728
  },
  {
    "account_id": "zkv_staketosupportprivacy.poolv1.near",
    "public_key": "ed25519:2kAo86DW8mDaLDg37rFhQY8UYSZVq1CtegUHBEDvpSMA",
    "is_slashed": false,
    "stake": "3679158958556029687466911013831",
    "shards": [
      0
    ],
    "num_produced_blocks": 432,
    "num_expected_blocks": 432
  }
]